{"cameraMode":{"drawMode":0,"name":"Shaded","section":"Shading Mode"},"sceneLighting":true,"audioPlay":false,"sceneViewState":{"m_AlwaysRefresh":false,"showFog":true,"showSkybox":true,"showFlares":true,"showImageEffects":true,"showParticleSystems":true,"showVisualEffectGraphs":true,"m_FxEnabled":true},"in2DMode":false,"pivot":{"x":0.3465217351913452,"y":1.529889702796936,"z":0.48803579807281496},"rotation":{"x":-0.12531597912311555,"y":0.33407828211784365,"z":-0.044864725321531299,"w":-0.933111846446991},"size":0.519166111946106,"orthographic":false}